nonebot_plugin_afd/__init__.py
nonebot_plugin_afd/config.py
nonebot_plugin_afd/group_new_member.py
nonebot_plugin_afd/order_notice.py
nonebot_plugin_afd/utils.py
nonebot_plugin_afd-0.1.1.dist-info/METADATA
nonebot_plugin_afd-0.1.1.dist-info/WHEEL
nonebot_plugin_afd-0.1.1.dist-info/licenses/LICENSE
nonebot_plugin_afd-0.1.1.dist-info/RECORD
