Metadata-Version: 2.4
Name: nonebot-plugin-afd
Version: 0.1.1
Summary: 基于NoneBot2的爱发电订单审核进群插件
Author-email: 17TheWord <17theword@gmail.com>
License-Expression: MIT
License-File: LICENSE
Requires-Python: <4,>=3.10
Requires-Dist: nonebot-adapter-afdian<0.2,>=0.1.8
Requires-Dist: nonebot-adapter-onebot<3,>=2.4.4
Requires-Dist: nonebot2[fastapi,httpx]<3,>=2.3.3
